MANIFEST.in
README.md
setup.py
tromegle/__init__.py
tromegle/core.py
tromegle/event.py
tromegle/listener.py
tromegle/omegle.py
tromegle/troll.py
tromegle.egg-info/PKG-INFO
tromegle.egg-info/SOURCES.txt
tromegle.egg-info/dependency_links.txt
tromegle.egg-info/requires.txt
tromegle.egg-info/top_level.txt