Metadata-Version: 1.0
Name: tromegle
Version: 0.1.0.alpha
Summary: Troll strangers!
Home-page: https://github.com/louist87/tromegle
Author: Louis Thibault
Author-email: UNKNOWN
License: GPL 3.0
Keywords: omegle,trolling
Platform: UNKNOWN
